pygenomecomp/__init__.py
pygenomecomp/annotation.py
pygenomecomp/blast.py
pygenomecomp/main.py
pygenomecomp/plot.py
pygenomecomp-0.2.0.dist-info/licenses/LICENSE
pygenomecomp-0.2.0.dist-info/METADATA
pygenomecomp-0.2.0.dist-info/WHEEL
pygenomecomp-0.2.0.dist-info/entry_points.txt
pygenomecomp-0.2.0.dist-info/top_level.txt
pygenomecomp-0.2.0.dist-info/RECORD
