Metadata-Version: 2.4
Name: pygenomecomp
Version: 0.2.0
Summary: A tool to create circular comparison plots for multiple genome assemblies against a reference.
Author-email: Yair Motro <your.email@example.com>
License: MIT License
Project-URL: Homepage, https://github.com/motroy/pygenomecomp
Project-URL: Bug Tracker, https://github.com/motroy/pygenomecomp/issues
Classifier: Programming Language :: Python :: 3
Classifier: License :: OSI Approved :: MIT License
Classifier: Operating System :: OS Independent
Classifier: Topic :: Scientific/Engineering :: Bio-Informatics
Classifier: Environment :: Console
Requires-Python: >=3.8
License-File: LICENSE
Requires-Dist: biopython>=1.80
Requires-Dist: pandas>=1.5
Requires-Dist: svgwrite>=1.4
Dynamic: license-file
